exthread
