Metadata-Version: 1.1
Name: exthread
Version: 0.1.1
Summary: Supercharged threads
Home-page: https://github.com/eugene-eeo/exthread/
Author: Eeo Jun
Author-email: packwolf58@gmail.com
License: UNKNOWN
Platform: any
Classifier: License :: OSI Approved :: MIT License
Classifier: Programming Language :: Python
Classifier: Programming Language :: Python :: 2
Classifier: Programming Language :: Python :: 3
